auto_augment/__init__.py
auto_augment/third_party/PaddleClas/.pre-commit-config.yaml
auto_augment/third_party/PaddleClas/requirements.txt
auto_augment/third_party/PaddleClas/.gitignore
auto_augment/third_party/PaddleClas/README.md
auto_augment/third_party/PaddleClas/LICENSE
auto_augment/third_party/PaddleClas/ppcls/__init__.py
auto_augment/third_party/PaddleClas/ppcls/data/__init__.py
auto_augment/third_party/PaddleClas/ppcls/data/reader.py
auto_augment/third_party/PaddleClas/ppcls/data/imaug/operators.py
auto_augment/third_party/PaddleClas/ppcls/data/imaug/randaugment.py
auto_augment/third_party/PaddleClas/ppcls/data/imaug/batch_operators.py
auto_augment/third_party/PaddleClas/ppcls/data/imaug/cutout.py
auto_augment/third_party/PaddleClas/ppcls/data/imaug/grid.py
auto_augment/third_party/PaddleClas/ppcls/data/imaug/__init__.py
auto_augment/third_party/PaddleClas/ppcls/data/imaug/hide_and_seek.py
auto_augment/third_party/PaddleClas/ppcls/data/imaug/random_erasing.py
auto_augment/third_party/PaddleClas/ppcls/data/imaug/fmix.py
auto_augment/third_party/PaddleClas/ppcls/data/imaug/autoaugment.py
auto_augment/third_party/PaddleClas/ppcls/utils/model_zoo.py
auto_augment/third_party/PaddleClas/ppcls/utils/misc.py
auto_augment/third_party/PaddleClas/ppcls/utils/pretrained.list
auto_augment/third_party/PaddleClas/ppcls/utils/save_load.py
auto_augment/third_party/PaddleClas/ppcls/utils/__init__.py
auto_augment/third_party/PaddleClas/ppcls/utils/config.py
auto_augment/third_party/PaddleClas/ppcls/utils/logger.py
auto_augment/third_party/PaddleClas/ppcls/utils/check.py
auto_augment/third_party/PaddleClas/ppcls/optimizer/optimizer.py
auto_augment/third_party/PaddleClas/ppcls/optimizer/learning_rate.py
auto_augment/third_party/PaddleClas/ppcls/optimizer/__init__.py
auto_augment/third_party/PaddleClas/ppcls/modeling/loss.py
auto_augment/third_party/PaddleClas/ppcls/modeling/__init__.py
auto_augment/third_party/PaddleClas/ppcls/modeling/utils.py
auto_augment-1.0.0.dist-info/RECORD
auto_augment-1.0.0.dist-info/top_level.txt
auto_augment-1.0.0.dist-info/METADATA
auto_augment-1.0.0.dist-info/LICENSE
auto_augment-1.0.0.dist-info/WHEEL
