Metadata-Version: 2.1
Name: auto-augment
Version: 1.0.0
Summary: "auto data augment for deep learining task"
Home-page: http://icode.baidu.com/repos/baidu/aicc/auto-augment/tree/master
Author: lishupeng
Author-email: lishupeng@baidu.com
License: Apache License 2.0
Platform: UNKNOWN
Classifier: Programming Language :: Python
Classifier: Programming Language :: Python :: 3
Classifier: Programming Language :: Python :: 3.7
Requires-Python: ~=3.7
Requires-Dist: albumentations (==0.4.3)
Requires-Dist: Cython (==0.29.16)
Requires-Dist: pycocotools (==2.0.0)
Requires-Dist: numpy
Requires-Dist: ray[tune] (==0.8.4)
Requires-Dist: scikit-learn
Requires-Dist: addict (==2.2.1)
Requires-Dist: xmltodict (==0.12.0)
Requires-Dist: pandas
Requires-Dist: ujson (==3.0.0)
